{
  "seller": {
    "user": {
      "id": "135647827",
      "name": "abirprantoap",
      "isActivationCompleted": true,
      "joinedAt": 1665125571,
      "profile": {
        "displayName": "Abir Ap"
      },
      "address": {
        "countryName": "Bangladesh",
        "countryCode": "BD"
      },
      "languages": [
        {
          "code": "EN",
          "level": "FLUENT"
        },
        {
          "code": "HI",
          "level": "CONVERSATIONAL"
        },
        {
          "code": "UR",
          "level": "CONVERSATIONAL"
        },
        {
          "code": "BN",
          "level": "NATIVE_OR_BILINGUAL"
        }
      ],
      "profileImageUrl": "https://fiverr-res.cloudinary.com/image/upload/f_auto,q_auto,t_profile_original/v1/attachments/profile/photo/4b3f8c1b91567f5d8ac6b81d5483b8ed-1699459892305/6c2a119b-743a-4aef-9d97-6704856dc60e.jpg"
    },
    "approvedGigsCount": 4,
    "gigs": {
      "nodes": [
        {
          "id": "311033154"
        },
        {
          "id": "319719924"
        },
        {
          "id": "341997940"
        },
        {
          "id": "346672617"
        }
      ]
    },
    "notableClients": [],
    "isActive": true,
    "introVideo": {
      "url": null
    },
    "oneLinerTitle": "I'm Graphics Designer 5 Years of Experience",
    "description": "Welcome to my graphics design service on Fiverr!\nI'am a professional graphic designer with several years of experience in creating high-quality designs for business and individuals.\nI work closely with my clients to understand their vision and goals.\nSo, if you're looking for a professional designer who can bring your ideas to life, look no further! \nContact me today to discuss your project and let's create something amazing/unique togather.",
    "isVerified": false,
    "hasLoyaltyScores": false,
    "isHighlyResponsive": false,
    "profileBackgroundImage": null,
    "certifications": [],
    "activeEducations": [
      {
        "degree": "diploma in computer engineering",
        "toYear": 2021,
        "countryCode": "BD",
        "school": "Life Line Polytechnic institute",
        "degreeTitle": "OTHER"
      }
    ],
    "activeStructuredSkills": [
      {
        "id": "617fa6510565f07789006037",
        "name": "Flyer design",
        "level": "PRO",
        "verified": false,
        "professionAlias": "Flyer designer"
      },
      {
        "id": "617fa63d0565f07789005a69",
        "name": "Brochure design",
        "level": "PRO",
        "verified": false,
        "professionAlias": "Brochure designer"
      },
      {
        "id": "617fa6620565f07789006537",
        "name": "Logo design",
        "level": "PRO",
        "verified": false,
        "professionAlias": "Logo designer"
      },
      {
        "id": "617fa6450565f07789005cd3",
        "name": "Customer service",
        "level": "PRO",
        "verified": true,
        "professionAlias": "Customer service representative"
      },
      {
        "id": "617fa6350565f077890057f6",
        "name": "Adobe Photoshop",
        "level": "PRO",
        "verified": true,
        "professionAlias": "Adobe Photoshop expert"
      },
      {
        "id": "617fa6350565f077890057ee",
        "name": "Adobe Illustrator",
        "level": "PRO",
        "verified": true,
        "professionAlias": "Adobe Illustrator expert"
      }
    ],
    "gigCategories": [
      {
        "categoryId": 3,
        "subCategoryId": 55,
        "nestedCategoryId": null
      }
    ],
    "isPro": false,
    "proSubCategories": [],
    "portfolios": {
      "nodes": [],
      "totalCount": 0
    },
    "onlinePresences": [],
    "professionalPresences": [],
    "courses": {
      "nodes": []
    },
    "rating": {
      "score": 4.7,
      "count": 4
    },
    "isOnVacation": false,
    "vacation": null,
    "achievementLevel": null,
    "responseTime": {
      "inHours": 40
    },
    "testimonials": [],
    "consultations": {
      "freeConsultationsEligible": false
    },
    "schedulingSettings": null,
    "agency": null
  },
  "currency": {
    "name": "PKR",
    "rate": 292.9524782706,
    "template": "₨{{amount}}",
    "forceRound": true,
    "forceRoundFromAmount": 0,
    "symbol": "₨"
  },
  "rollouts": {
    "grizzlies_trader_details_displaying": false
  },
  "reviewsData": {
    "buying_reviews": {
      "reviews": [
        {
          "id": "658db956d628ec0001852835",
          "comment": "I love working with Abir Ap\nHe is so patient and I appreciate his service smooth and fast. over delivers.",
          "comment_language": "en",
          "username": "kttyler",
          "reviewer_country_code": "US",
          "created_at": "2023-12-28T18:23:03",
          "value": 5,
          "reviewer_country": "United States",
          "encrypted_order_id": "FO3BE948D741",
          "score": 0.19801429,
          "repeat_buyer": true,
          "is_business": false,
          "gig_id": 346672617,
          "gig_slug": "design-event-flyer-poster-brochure-company-profile-magazine-anual-report-epk-pdf",
          "gig_category": 3,
          "gig_sub_category": 55,
          "relevancy_score": 1,
          "price_range_start": 2500,
          "price_range_end": 5000,
          "reviews_count_as_buyer": 8,
          "is_cancelled_order": false,
          "original_relevancy_score": 1
        },
        {
          "id": "6576986ca20623000191ae93",
          "comment": "Abir Ap\nwas Excellent to work with. I definitely recommend you give him an opportunity. He was polite and very responsive. I will definitely use him again. ",
          "comment_language": "en",
          "username": "kttyler",
          "reviewer_country_code": "US",
          "created_at": "2023-12-11T05:07:04",
          "value": 5,
          "reviewer_country": "United States",
          "encrypted_order_id": "FO72399B5C3C5",
          "score": 0,
          "repeat_buyer": true,
          "is_business": false,
          "gig_id": 346672617,
          "gig_slug": "design-event-flyer-poster-brochure-company-profile-magazine-anual-report-epk-pdf",
          "gig_category": 3,
          "gig_sub_category": 55,
          "relevancy_score": 0,
          "price_range_start": 1000,
          "price_range_end": 2500,
          "reviews_count_as_buyer": 8,
          "is_cancelled_order": false
        },
        {
          "id": "655c4d47e4ce96000133701a",
          "comment": "Great. You get what you pay for. ",
          "comment_language": "en",
          "username": "stanopltd",
          "reviewer_country_code": "GB",
          "user_image_url": "https://fiverr-res.cloudinary.com/image/upload/f_auto,q_auto,t_profile_small/v1/attachments/profile/photo/95588c2f7c66c66f19c826df517fbcea-1700057311024/d4e6ff2e-d16e-4809-8bdd-9eddaccf1a6a.png",
          "created_at": "2023-11-21T06:30:42",
          "value": 3.7,
          "work_sample": "https://fiverr-res.cloudinary.com/image/upload/c_limit,f_auto,q_auto,t_smartwm,w_500/v1/attachments/delivery/asset/331eb51ad182ac6ac27b2d4026d310ed-1700547668/Artboard%201.png",
          "work_sample_small": "https://fiverr-res.cloudinary.com/image/upload/f_auto,q_auto,t_smartwm/t_delivery_small/v1/attachments/delivery/asset/331eb51ad182ac6ac27b2d4026d310ed-1700547668/Artboard%201.png",
          "reviewer_country": "United Kingdom",
          "encrypted_order_id": "FO82F3DA31B08",
          "score": 0,
          "reviewer_industry": [],
          "repeat_buyer": false,
          "is_business": false,
          "gig_id": 346672617,
          "gig_slug": "design-event-flyer-poster-brochure-company-profile-magazine-anual-report-epk-pdf",
          "gig_category": 3,
          "gig_sub_category": 55,
          "relevancy_score": 0,
          "price_range_start": 1000,
          "price_range_end": 2500,
          "reviews_count_as_buyer": 1,
          "is_cancelled_order": false
        },
        {
          "id": "6538a6910847ab00015a30df",
          "comment": "Fantastic work & delivered as expected without any argument. I definitely recommend, and will use services in the future if needed. Thanks again for your patience.",
          "comment_language": "en",
          "username": "ideal_max",
          "reviewer_country_code": "US",
          "created_at": "2023-10-25T05:53:29",
          "value": 5,
          "work_sample": "https://fiverr-res.cloudinary.com/image/upload/c_limit,f_auto,q_auto,t_smartwm,w_500/v1/attachments/delivery/asset/572ea2b6c7c31557cc5f0a45ac9e689a-1698208866/Burger%20hut%20Thakurgaon.png",
          "work_sample_small": "https://fiverr-res.cloudinary.com/image/upload/f_auto,q_auto,t_smartwm/t_delivery_small/v1/attachments/delivery/asset/572ea2b6c7c31557cc5f0a45ac9e689a-1698208866/Burger%20hut%20Thakurgaon.png",
          "reviewer_country": "United States",
          "encrypted_order_id": "FO111985B3F45",
          "score": 0,
          "repeat_buyer": false,
          "is_business": false,
          "gig_id": 346672617,
          "gig_slug": "design-event-flyer-poster-brochure-company-profile-magazine-anual-report-epk-pdf",
          "gig_category": 3,
          "gig_sub_category": 55,
          "relevancy_score": 0,
          "price_range_start": 2500,
          "price_range_end": 5000,
          "reviews_count_as_buyer": 85,
          "is_cancelled_order": false,
          "original_relevancy_score": 1
        }
      ],
      "has_next": false,
      "total_count": 4,
      "reviews_as_seller": true,
      "filters_counters": {
        "work_sample": 4
      },
      "user_id": 135647827,
      "seller_username": "abirprantoap",
      "star_summary": {
        "communication_valuation": 5,
        "recommend_valuation": 4.5,
        "service_valuation": 4.5
      },
      "breakdown": [
        {
          "average_valuation_value": 1,
          "count": 0
        },
        {
          "average_valuation_value": 2,
          "count": 0
        },
        {
          "average_valuation_value": 3,
          "count": 0
        },
        {
          "average_valuation_value": 4,
          "count": 1
        },
        {
          "average_valuation_value": 5,
          "count": 3
        }
      ],
      "average_valuation": 4.7
    },
    "selling_reviews": {
      "user_id": 135647827,
      "reviews": [],
      "total_count": null,
      "average_valuation": null,
      "reviews_as_seller": false,
      "has_next": false
    }
  },
  "consultationData": {},
  "localizationData": {
    "user_id": 135647827,
    "currency": "USD",
    "locale": "en-US",
    "timezone": "Asia/Dhaka",
    "recent_utc_offset": -360
  },
  "gigsData": [
    {
      "gig_id": 346672617,
      "category_id": 3,
      "sub_category_id": 55,
      "nested_sub_category_id": 0,
      "is_pro": false,
      "is_featured": false,
      "cached_slug": "design-event-flyer-poster-brochure-company-profile-magazine-anual-report-epk-pdf",
      "title": "design event flyer poster brochure company profile magazine anual report epk pdf",
      "seller_name": "abirprantoap",
      "seller_id": 135647827,
      "seller_country": "BD",
      "seller_img": "https://fiverr-res.cloudinary.com/t_profile_thumb,q_auto,f_auto/attachments/profile/photo/4b3f8c1b91567f5d8ac6b81d5483b8ed-1699459892305/6c2a119b-743a-4aef-9d97-6704856dc60e.jpg",
      "seller_display_name": "Abir Ap",
      "seller_online": false,
      "status": "APPROVED",
      "offer_consultation": false,
      "assets": [
        {
          "cloud_img_main_gig": "https://fiverr-res.cloudinary.com/t_main1,q_auto,f_auto/gigs/346672617/original/79e3d4b75f207e19ee963f346b951b8b6cb7d0b0.jpg",
          "type": "ImageAsset",
          "id": "346672617_1"
        },
        {
          "cloud_img_main_gig": "https://fiverr-res.cloudinary.com/t_main1,q_auto,f_auto/gigs2/346672617/original/fa3c1d4e5b05d7984c79676b370ea1eed584ce0f.png",
          "type": "ImageAsset",
          "id": "346672617_2"
        },
        {
          "cloud_img_main_gig": "https://fiverr-res.cloudinary.com/t_main1,q_auto,f_auto/gigs3/346672617/original/a1e942c57f01794834be7e1e29dade1f0a49fc18.png",
          "type": "ImageAsset",
          "id": "346672617_3"
        }
      ],
      "filtered_delivery_attachments": [
        {
          "id": "173471660",
          "image_url": "https://fiverr-res.cloudinary.com/PLACEHOLDER,q_auto,f_auto/attachments/delivery/asset/331eb51ad182ac6ac27b2d4026d310ed-1700547668/Artboard%201.png",
          "is_visible": true,
          "type": "image"
        },
        {
          "id": "172297213",
          "image_url": "https://fiverr-res.cloudinary.com/PLACEHOLDER,q_auto,f_auto/attachments/delivery/asset/572ea2b6c7c31557cc5f0a45ac9e689a-1698208866/Burger%20hut%20Thakurgaon.png",
          "is_visible": true,
          "type": "image"
        }
      ],
      "choice_eligibilities": null,
      "seller_languages": [
        {
          "code": "en",
          "level": 3
        },
        {
          "code": "hi",
          "level": 2
        },
        {
          "code": "ur",
          "level": 2
        },
        {
          "code": "bn",
          "level": 4
        }
      ],
      "recurring_options": null,
      "metadata": [
        {
          "type": "main_type",
          "value": [
            "flyers_brochures",
            "media_kit"
          ]
        },
        {
          "type": "image_file_format",
          "value": [
            "ai",
            "jpg",
            "pdf",
            "png",
            "psd"
          ]
        }
      ],
      "personalized_pricing_fail": false,
      "has_recurring_option": false,
      "buying_review_rating_count": 4,
      "buying_review_rating": 4.7,
      "seller_url": "/abirprantoap",
      "seller_level": "",
      "seller_rating": {
        "count": 4,
        "score": 4.6666665
      },
      "gig_url": "/abirprantoap/design-event-flyer-poster-brochure-company-profile-magazine-anual-report-epk-pdf",
      "is_seller_unavailable": false,
      "price_i": 5,
      "package_i": 1,
      "extra_fast": false,
      "num_of_packages": 3,
      "gigQueryParams": {}
    },
    {
      "gig_id": 311033154,
      "category_id": 3,
      "sub_category_id": 55,
      "nested_sub_category_id": 0,
      "is_pro": false,
      "is_featured": false,
      "cached_slug": "eye-catching-flyer-designs-to-promote-your-business-or-event-e7c2",
      "title": "design a flyer brochure banner leaflet under 6 hour",
      "seller_name": "abirprantoap",
      "seller_id": 135647827,
      "seller_country": "BD",
      "seller_img": "https://fiverr-res.cloudinary.com/t_profile_thumb,q_auto,f_auto/attachments/profile/photo/4b3f8c1b91567f5d8ac6b81d5483b8ed-1699459892305/6c2a119b-743a-4aef-9d97-6704856dc60e.jpg",
      "seller_display_name": "Abir Ap",
      "seller_online": false,
      "status": "APPROVED",
      "offer_consultation": false,
      "assets": [
        {
          "cloud_img_main_gig": "https://fiverr-res.cloudinary.com/t_main1,q_auto,f_auto/gigs/311033154/original/dc81d3248068e91a8e453167d2813e0f44abf421.png",
          "type": "ImageAsset",
          "id": "311033154_1"
        },
        {
          "cloud_img_main_gig": "https://fiverr-res.cloudinary.com/t_main1,q_auto,f_auto/gigs2/311033154/original/aabdacbc262ab95bb13558b1badc5ca8bc8c7b6a.png",
          "type": "ImageAsset",
          "id": "311033154_2"
        },
        {
          "cloud_img_main_gig": "https://fiverr-res.cloudinary.com/t_main1,q_auto,f_auto/gigs3/311033154/original/c118768c01068ec648a4b2a09f643ff163db144b.png",
          "type": "ImageAsset",
          "id": "311033154_3"
        }
      ],
      "choice_eligibilities": null,
      "seller_languages": [
        {
          "code": "en",
          "level": 3
        },
        {
          "code": "hi",
          "level": 2
        },
        {
          "code": "ur",
          "level": 2
        },
        {
          "code": "bn",
          "level": 4
        }
      ],
      "recurring_options": null,
      "metadata": [
        {
          "type": "main_type",
          "value": [
            "flyers_brochures",
            "media_kit"
          ]
        },
        {
          "type": "image_file_format",
          "value": [
            "ai",
            "jpg",
            "psd"
          ]
        }
      ],
      "personalized_pricing_fail": false,
      "has_recurring_option": false,
      "buying_review_rating_count": 0,
      "buying_review_rating": 0,
      "seller_url": "/abirprantoap",
      "seller_level": "",
      "seller_rating": {
        "count": 4,
        "score": 4.6666665
      },
      "gig_url": "/abirprantoap/eye-catching-flyer-designs-to-promote-your-business-or-event-e7c2",
      "is_seller_unavailable": false,
      "price_i": 5,
      "package_i": 1,
      "extra_fast": false,
      "num_of_packages": 3,
      "gigQueryParams": {}
    },
    {
      "gig_id": 319719924,
      "category_id": 3,
      "sub_category_id": 55,
      "nested_sub_category_id": 0,
      "is_pro": false,
      "is_featured": false,
      "cached_slug": "design-professional-flyers-and-posters-within-6-hours",
      "title": "design professional flyers and posters within 6 hours",
      "seller_name": "abirprantoap",
      "seller_id": 135647827,
      "seller_country": "BD",
      "seller_img": "https://fiverr-res.cloudinary.com/t_profile_thumb,q_auto,f_auto/attachments/profile/photo/4b3f8c1b91567f5d8ac6b81d5483b8ed-1699459892305/6c2a119b-743a-4aef-9d97-6704856dc60e.jpg",
      "seller_display_name": "Abir Ap",
      "seller_online": false,
      "status": "APPROVED",
      "offer_consultation": false,
      "assets": [
        {
          "cloud_img_main_gig": "https://fiverr-res.cloudinary.com/t_main1,q_auto,f_auto/gigs/319719924/original/5682fa92124af6996d086a5c8f6fed0750644ff6.png",
          "type": "ImageAsset",
          "id": "319719924_1"
        },
        {
          "cloud_img_main_gig": "https://fiverr-res.cloudinary.com/t_main1,q_auto,f_auto/gigs2/319719924/original/8521c5fb17f27a3f5c7ee815c260d57bae8df6ce.png",
          "type": "ImageAsset",
          "id": "319719924_2"
        }
      ],
      "choice_eligibilities": null,
      "seller_languages": [
        {
          "code": "en",
          "level": 3
        },
        {
          "code": "hi",
          "level": 2
        },
        {
          "code": "ur",
          "level": 2
        },
        {
          "code": "bn",
          "level": 4
        }
      ],
      "recurring_options": null,
      "metadata": [
        {
          "type": "main_type",
          "value": [
            "flyers_brochures",
            "media_kit"
          ]
        },
        {
          "type": "image_file_format",
          "value": [
            "ai",
            "jpg",
            "pdf",
            "png",
            "psd"
          ]
        }
      ],
      "personalized_pricing_fail": false,
      "has_recurring_option": false,
      "buying_review_rating_count": 0,
      "buying_review_rating": 0,
      "seller_url": "/abirprantoap",
      "seller_level": "",
      "seller_rating": {
        "count": 4,
        "score": 4.6666665
      },
      "gig_url": "/abirprantoap/design-professional-flyers-and-posters-within-6-hours",
      "is_seller_unavailable": false,
      "price_i": 10,
      "package_i": 1,
      "extra_fast": false,
      "num_of_packages": 3,
      "gigQueryParams": {}
    },
    {
      "gig_id": 341997940,
      "category_id": 3,
      "sub_category_id": 55,
      "nested_sub_category_id": 0,
      "is_pro": false,
      "is_featured": false,
      "cached_slug": "design-professional-flyers-and-posters-within-6-hours-9b78",
      "title": "design party flyer poster event company profile magazine anual report epk",
      "seller_name": "abirprantoap",
      "seller_id": 135647827,
      "seller_country": "BD",
      "seller_img": "https://fiverr-res.cloudinary.com/t_profile_thumb,q_auto,f_auto/attachments/profile/photo/4b3f8c1b91567f5d8ac6b81d5483b8ed-1699459892305/6c2a119b-743a-4aef-9d97-6704856dc60e.jpg",
      "seller_display_name": "Abir Ap",
      "seller_online": false,
      "status": "APPROVED",
      "offer_consultation": false,
      "assets": [
        {
          "cloud_img_main_gig": "https://fiverr-res.cloudinary.com/t_main1,q_auto,f_auto/gigs/341997940/original/7be2f3918f8eebe9e628c941bc98f17cb627b729.png",
          "type": "ImageAsset",
          "id": "341997940_1"
        },
        {
          "cloud_img_main_gig": "https://fiverr-res.cloudinary.com/t_main1,q_auto,f_auto/gigs2/341997940/original/99bd929d310840bb1b73b7cd92617e8cb31e4a9f.png",
          "type": "ImageAsset",
          "id": "341997940_2"
        },
        {
          "cloud_img_main_gig": "https://fiverr-res.cloudinary.com/t_main1,q_auto,f_auto/gigs3/341997940/original/b91eded90facffbc3687307b06b0138cdf9a53f9.png",
          "type": "ImageAsset",
          "id": "341997940_3"
        }
      ],
      "choice_eligibilities": null,
      "seller_languages": [
        {
          "code": "en",
          "level": 3
        },
        {
          "code": "hi",
          "level": 2
        },
        {
          "code": "ur",
          "level": 2
        },
        {
          "code": "bn",
          "level": 4
        }
      ],
      "recurring_options": null,
      "metadata": [
        {
          "type": "main_type",
          "value": [
            "flyers_brochures"
          ]
        },
        {
          "type": "image_file_format",
          "value": [
            "ai",
            "jpg",
            "png",
            "psd"
          ]
        }
      ],
      "personalized_pricing_fail": false,
      "has_recurring_option": false,
      "buying_review_rating_count": 0,
      "buying_review_rating": 0,
      "seller_url": "/abirprantoap",
      "seller_level": "",
      "seller_rating": {
        "count": 4,
        "score": 4.6666665
      },
      "gig_url": "/abirprantoap/design-professional-flyers-and-posters-within-6-hours-9b78",
      "is_seller_unavailable": false,
      "price_i": 5,
      "package_i": 1,
      "extra_fast": false,
      "num_of_packages": 3,
      "gigQueryParams": {}
    }
  ]
}