{
  "seller": {
    "user": {
      "id": "148673161",
      "name": "deb_prodip",
      "isActivationCompleted": true,
      "joinedAt": 1680702247,
      "profile": {
        "displayName": "Prodip Chandra"
      },
      "address": {
        "countryName": "Bangladesh",
        "countryCode": "BD"
      },
      "languages": [
        {
          "code": "EN",
          "level": "FLUENT"
        },
        {
          "code": "NL",
          "level": "CONVERSATIONAL"
        },
        {
          "code": "ES",
          "level": "CONVERSATIONAL"
        },
        {
          "code": "FR",
          "level": "CONVERSATIONAL"
        }
      ],
      "profileImageUrl": "https://fiverr-res.cloudinary.com/image/upload/f_auto,q_auto,t_profile_original/v1/attachments/profile/photo/0a3b28ff6f48ff06ce78088d27dae350-1687456842383/0418ca90-f619-4a05-9e4a-c63e4f5f13cd.jpg"
    },
    "approvedGigsCount": 1,
    "gigs": {
      "nodes": [
        {
          "id": "358555440"
        }
      ]
    },
    "notableClients": [],
    "isActive": true,
    "introVideo": {
      "url": null
    },
    "oneLinerTitle": null,
    "description": "I am an experienced Digital Marketer, proficient in a myriad of online marketing techniques, such as Search Engine Optimization (SEO), Social Media Marketing like Facebook & Google ads, YouTube Video SEO, Leads Generation, Email Marketing, Shopify Klaviyo, and much more. My forte lies in aiding enterprises, small and large, across all industries, to construct an imposing digital identity, enhance website traffic, amass leads, and augment sales. I aim to furnish my clients with tailor-made and efficacious digital marketing strategies that aid them in realizing their commercial goals.",
    "isVerified": false,
    "hasLoyaltyScores": false,
    "isHighlyResponsive": false,
    "profileBackgroundImage": null,
    "certifications": [
      {
        "receivedFrom": "Outcoursing Institute in BD",
        "certificationName": "Digital Marketing",
        "year": 2022
      }
    ],
    "activeEducations": [
      {
        "degree": "national diplomapublic administration",
        "toYear": 2022,
        "countryCode": "BD",
        "school": "outsourcing institute in BD",
        "degreeTitle": "ASSOCIATE"
      },
      {
        "degree": "deploma",
        "toYear": 2021,
        "countryCode": "BD",
        "school": "Dinajpur Polytechnic Institute",
        "degreeTitle": "OTHER"
      }
    ],
    "activeStructuredSkills": [
      {
        "id": "617fa64f0565f07789005f72",
        "name": "Facebook ads",
        "level": "PRO",
        "verified": false,
        "professionAlias": "Facebook ads expert"
      },
      {
        "id": "617fa6600565f077890064ab",
        "name": "Lead generation",
        "level": "PRO",
        "verified": false,
        "professionAlias": "Lead generation expert"
      },
      {
        "id": "617fa6790565f07789006bdc",
        "name": "Virtual assistance",
        "level": "PRO",
        "verified": false,
        "professionAlias": "Virtual assistant"
      },
      {
        "id": "617fa64b0565f07789005e82",
        "name": "Email marketing",
        "level": "PRO",
        "verified": false,
        "professionAlias": "Email marketer"
      },
      {
        "id": "617fa6710565f0778900696f",
        "name": "Shopify marketing",
        "level": "PRO",
        "verified": false,
        "professionAlias": "Shopify marketing expert"
      },
      {
        "id": "617fa6700565f0778900694c",
        "name": "SEO",
        "level": "PRO",
        "verified": false,
        "professionAlias": "SEO expert"
      },
      {
        "id": "617fa64f0565f07789005f7e",
        "name": "Facebook management",
        "level": "PRO",
        "verified": false,
        "professionAlias": "Facebook manager"
      },
      {
        "id": "617fa65f0565f07789006465",
        "name": "Klaviyo",
        "level": "PRO",
        "verified": false,
        "professionAlias": "Klaviyo expert"
      },
      {
        "id": "617fa6550565f07789006172",
        "name": "Google ads",
        "level": "PRO",
        "verified": false,
        "professionAlias": "Google ad manager"
      },
      {
        "id": "617fa67e0565f07789006d53",
        "name": "YouTube SEO",
        "level": "PRO",
        "verified": false,
        "professionAlias": "YouTube SEO expert"
      }
    ],
    "gigCategories": [
      {
        "categoryId": 2,
        "subCategoryId": 69,
        "nestedCategoryId": 2083
      }
    ],
    "isPro": false,
    "proSubCategories": [],
    "portfolios": {
      "nodes": [],
      "totalCount": 0
    },
    "onlinePresences": [],
    "professionalPresences": [],
    "courses": {
      "nodes": []
    },
    "rating": {
      "score": 5,
      "count": 5
    },
    "isOnVacation": false,
    "vacation": null,
    "achievementLevel": null,
    "responseTime": {
      "inHours": 1
    },
    "testimonials": [],
    "consultations": {
      "freeConsultationsEligible": false
    },
    "schedulingSettings": null,
    "agency": null
  },
  "currency": {
    "name": "PKR",
    "rate": 293.548605,
    "template": "₨{{amount}}",
    "forceRound": true,
    "forceRoundFromAmount": 0,
    "symbol": "₨"
  },
  "rollouts": {
    "grizzlies_trader_details_displaying": false
  },
  "reviewsData": {
    "buying_reviews": {
      "reviews": [
        {
          "id": "65bfd403c23f2d000140069d",
          "comment": "I am very impressed that I disseminated\nmy video to a very specific targeted\naudience. The communication was excellent\nand the service was satisfactory. Will be\ncollaborating with him once more shortly!\nyou are the best.\nThanks Mr. Prodip Chandra",
          "comment_language": "en",
          "username": "hasanmahmudazad",
          "reviewer_country_code": "SA",
          "user_image_url": "https://fiverr-res.cloudinary.com/image/upload/f_auto,q_auto,t_profile_small/v1/attachments/profile/photo/3b776554e45f1cded201b810a3627493-1678046781704912887595/JPEG_20240110_215446_2224168109900706209.jpg",
          "created_at": "2024-02-04T18:22:09",
          "value": 5,
          "reviewer_country": "Saudi Arabia",
          "encrypted_order_id": "FO824061D49C4",
          "score": 0,
          "repeat_buyer": true,
          "is_business": false,
          "gig_id": 358555440,
          "gig_slug": "be-your-youtube-video-seo-expert-and-paid-promotion",
          "gig_category": 2,
          "gig_sub_category": 69,
          "gig_nested_sub_category": 2083,
          "relevancy_score": 0,
          "price_range_start": 1000,
          "price_range_end": 2500,
          "reviews_count_as_buyer": 3,
          "is_cancelled_order": false
        },
        {
          "id": "65bc6a39e4010a34516725ba",
          "comment": "Prodip demonstrates exceptional professionalism and a high level of skill. I am extremely pleased with the quality of his work and plan to collaborate with him again in the future. I highly recommend Prodip to anyone seeking to enhance their YouTube channel through paid ads. He is the perfect choice for the job.",
          "comment_language": "en",
          "username": "rosemarytsanche",
          "reviewer_country_code": "US",
          "user_image_url": "https://fiverr-res.cloudinary.com/image/upload/f_auto,q_auto,t_profile_small/v1/attachments/profile/photo/e68cffa034991e10645c0b120de18c19-1705738428498/7de43067-760d-4122-bd5c-781cd86c0dc6.jpg",
          "created_at": "2024-02-04T18:43:27",
          "value": 5,
          "reviewer_country": "United States",
          "encrypted_order_id": "FO6180316ED82",
          "score": 0,
          "reviewer_industry": [
            "marketing_or_advertising"
          ],
          "repeat_buyer": false,
          "is_business": false,
          "gig_id": 358555440,
          "gig_slug": "be-your-youtube-video-seo-expert-and-paid-promotion",
          "gig_category": 2,
          "gig_sub_category": 69,
          "gig_nested_sub_category": 2083,
          "relevancy_score": 0,
          "price_range_start": 1000,
          "price_range_end": 2500,
          "reviews_count_as_buyer": 34,
          "is_cancelled_order": false
        },
        {
          "id": "65b40449756b9d0001751e1e",
          "comment": "Fast and accurate, reviously reviews for\nearlier project. She followed my instructions\nand delivered the final package on time\nas promised. I would work with her again\nif a similar project were to come up. I\nrecommend this gig and appreciate the work",
          "comment_language": "en",
          "username": "hasanmahmudazad",
          "reviewer_country_code": "SA",
          "user_image_url": "https://fiverr-res.cloudinary.com/image/upload/f_auto,q_auto,t_profile_small/v1/attachments/profile/photo/3b776554e45f1cded201b810a3627493-1678046781704912887595/JPEG_20240110_215446_2224168109900706209.jpg",
          "created_at": "2024-01-27T17:17:32",
          "value": 5,
          "reviewer_country": "Saudi Arabia",
          "encrypted_order_id": "FO211F923B3C4",
          "score": 0,
          "repeat_buyer": true,
          "is_business": false,
          "gig_id": 358555440,
          "gig_slug": "be-your-youtube-video-seo-expert-and-paid-promotion",
          "gig_category": 2,
          "gig_sub_category": 69,
          "gig_nested_sub_category": 2083,
          "relevancy_score": 0,
          "price_range_start": 1000,
          "price_range_end": 2500,
          "reviews_count_as_buyer": 3,
          "is_cancelled_order": false
        },
        {
          "id": "65acc3f049d34f2171b3b3d2",
          "comment": "Prodip demonstrates exceptional professionalism and an impressive skill set. The level of communication was outstanding, and I am thoroughly pleased with the quality of work delivered. Without a doubt, I plan to collaborate with Prodip again in the future. I wholeheartedly recommend their services to anyone seeking to enhance their YouTube channel through paid advertising. Prodip is an ideal choice for those aiming to elevate their online presence.",
          "comment_language": "en",
          "username": "joshuajonees",
          "reviewer_country_code": "US",
          "user_image_url": "https://fiverr-res.cloudinary.com/image/upload/f_auto,q_auto,t_profile_small/v1/attachments/profile/photo/feb12eda326a4525461e2e454bb89cc8-1695447465196/2f95f678-d1c1-4381-b729-3ce004224d3b.jpg",
          "created_at": "2024-01-21T10:10:01",
          "value": 5,
          "reviewer_country": "United States",
          "encrypted_order_id": "FO2BF4705D42",
          "score": 0,
          "reviewer_industry": [],
          "repeat_buyer": false,
          "is_business": false,
          "gig_id": 358555440,
          "gig_slug": "be-your-youtube-video-seo-expert-and-paid-promotion",
          "gig_category": 2,
          "gig_sub_category": 69,
          "gig_nested_sub_category": 2083,
          "relevancy_score": 0,
          "price_range_start": 1000,
          "price_range_end": 2500,
          "reviews_count_as_buyer": 144,
          "is_cancelled_order": false
        },
        {
          "id": "65a849e02f49060001a254b4",
          "comment": "Highly satisfied work with Prodip chandra.Thank you for nicely done my project.hope we will work long term ",
          "comment_language": "en",
          "username": "hasanmahmudazad",
          "reviewer_country_code": "SA",
          "user_image_url": "https://fiverr-res.cloudinary.com/image/upload/f_auto,q_auto,t_profile_small/v1/attachments/profile/photo/3b776554e45f1cded201b810a3627493-1678046781704912887595/JPEG_20240110_215446_2224168109900706209.jpg",
          "created_at": "2024-01-17T21:48:12",
          "value": 5,
          "reviewer_country": "Saudi Arabia",
          "encrypted_order_id": "FO15FB0C6401",
          "score": 0,
          "repeat_buyer": true,
          "is_business": false,
          "gig_id": 358555440,
          "gig_slug": "be-your-youtube-video-seo-expert-and-paid-promotion",
          "gig_category": 2,
          "gig_sub_category": 69,
          "gig_nested_sub_category": 2083,
          "relevancy_score": 0,
          "price_range_start": 1000,
          "price_range_end": 2500,
          "reviews_count_as_buyer": 3,
          "is_cancelled_order": false
        }
      ],
      "has_next": false,
      "total_count": 5,
      "reviews_as_seller": true,
      "filters_counters": {
        "work_sample": 0,
        "business": 0
      },
      "user_id": 148673161,
      "seller_username": "deb_prodip",
      "star_summary": {
        "communication_valuation": 5,
        "recommend_valuation": 5,
        "service_valuation": 5
      },
      "breakdown": [
        {
          "average_valuation_value": 1,
          "count": 0
        },
        {
          "average_valuation_value": 2,
          "count": 0
        },
        {
          "average_valuation_value": 3,
          "count": 0
        },
        {
          "average_valuation_value": 4,
          "count": 0
        },
        {
          "average_valuation_value": 5,
          "count": 5
        }
      ],
      "average_valuation": 5,
      "dynamicTranslations": {
        "marketing_or_advertising": "Marketing & Advertising"
      }
    },
    "selling_reviews": {
      "user_id": 148673161,
      "reviews": [],
      "total_count": null,
      "average_valuation": null,
      "reviews_as_seller": false,
      "has_next": false
    }
  },
  "consultationData": {},
  "localizationData": {
    "user_id": 148673161,
    "currency": "USD",
    "locale": "en-US",
    "timezone": "Asia/Dhaka",
    "recent_utc_offset": -360
  },
  "gigsData": [
    {
      "gig_id": 358555440,
      "category_id": 2,
      "sub_category_id": 69,
      "nested_sub_category_id": 2083,
      "is_pro": false,
      "is_featured": false,
      "cached_slug": "be-your-youtube-video-seo-expert-and-paid-promotion",
      "title": "be your youtube video SEO expert and paid promotion",
      "seller_name": "deb_prodip",
      "seller_id": 148673161,
      "seller_country": "BD",
      "seller_img": "https://fiverr-res.cloudinary.com/t_profile_thumb,q_auto,f_auto/attachments/profile/photo/0a3b28ff6f48ff06ce78088d27dae350-1687456842383/0418ca90-f619-4a05-9e4a-c63e4f5f13cd.jpg",
      "seller_online": true,
      "status": "APPROVED",
      "offer_consultation": false,
      "assets": [
        {
          "cloud_img_main_gig": "https://fiverr-res.cloudinary.com/t_main1,q_auto,f_auto/gigs/358555440/original/130e3d74acddf6618d381bc293be5a324501c52d.png",
          "type": "ImageAsset",
          "id": "358555440_1"
        },
        {
          "cloud_img_main_gig": "https://fiverr-res.cloudinary.com/t_main1,q_auto,f_auto/gigs2/358555440/original/2ecb4490af0bbab06b7214104ec7153a1ae0bda8.png",
          "type": "ImageAsset",
          "id": "358555440_2"
        },
        {
          "cloud_img_main_gig": "https://fiverr-res.cloudinary.com/t_main1,q_auto,f_auto/gigs3/358555440/original/3b79d3a831972a72c4732f25c4412978889f447e.png",
          "type": "ImageAsset",
          "id": "358555440_3"
        }
      ],
      "choice_eligibilities": null,
      "seller_languages": [
        {
          "code": "en",
          "level": 3
        },
        {
          "code": "nl",
          "level": 2
        },
        {
          "code": "es",
          "level": 2
        },
        {
          "code": "fr",
          "level": 2
        }
      ],
      "recurring_options": null,
      "metadata": null,
      "personalized_pricing_fail": false,
      "has_recurring_option": false,
      "buying_review_rating_count": 5,
      "buying_review_rating": 5,
      "seller_url": "/deb_prodip",
      "seller_level": "",
      "seller_rating": {
        "count": 5,
        "score": 5
      },
      "gig_url": "/deb_prodip/be-your-youtube-video-seo-expert-and-paid-promotion",
      "is_seller_unavailable": false,
      "price_i": 40,
      "package_i": 1,
      "extra_fast": false,
      "num_of_packages": 3,
      "gigQueryParams": {}
    }
  ]
}